yandex_music_agent/__init__.py
yandex_music_agent/__main__.py
yandex_music_agent/agent.py
yandex_music_agent/api.py
yandex_music_agent/auth.py
yandex_music_agent/data.py
yandex_music_agent/filename.py
yandex_music_agent/main.py
yandex_music_agent/common/__init__.py
yandex_music_agent/common/form.py
yandex_music_agent/common/headers.py
yandex_music_agent/common/srcset.py
yandex_music_agent/common/storage.py
yandex_music_agent-0.3.0.dist-info/METADATA
yandex_music_agent-0.3.0.dist-info/WHEEL
yandex_music_agent-0.3.0.dist-info/entry_points.txt
yandex_music_agent-0.3.0.dist-info/top_level.txt
yandex_music_agent-0.3.0.dist-info/RECORD
