Metadata-Version: 2.1
Name: yandex-music-agent
Version: 0.3.0
Summary: Download yandex account favorites artists music
Home-page: https://bitbucket.org/shmyga/yandex-music-agent
Author: shmyga
Author-email: shmyga.z@gmail.com
License: MIT
Platform: UNKNOWN
Requires-Python: >=3.7
Requires-Dist: aiostream (>=0)
Requires-Dist: appdirs (>=1)
Requires-Dist: argparse (>=1)
Requires-Dist: beautifulsoup4 (>=4)
Requires-Dist: brotlipy (>=0)
Requires-Dist: lxml (>=4)
Requires-Dist: mechanicus (>=0)
Requires-Dist: mutagen (>=1)
